msal_streamlit_auth/__init__.py
msal_streamlit_auth/frontend/dist/assets/index-CNkUTRnU.css
msal_streamlit_auth/frontend/dist/assets/index-fnI2Rijh.js
msal_streamlit_auth/frontend/dist/index.html
msal_streamlit_auth-1.1.4.dist-info/METADATA
msal_streamlit_auth-1.1.4.dist-info/WHEEL
msal_streamlit_auth-1.1.4.dist-info/licenses/LICENSE
msal_streamlit_auth-1.1.4.dist-info/RECORD
