Metadata-Version: 2.4
Name: msal_streamlit_auth
Version: 1.1.4
Summary: Streamlit auth library based on MSAL.JS
License-File: LICENSE
Author: Matthew Pallotta
Author-email: matthew.pallotta@independenthealth.com
Requires-Python: >=3.9,<3.14
Classifier: Programming Language :: Python :: 3
Classifier: Programming Language :: Python :: 3.9
Classifier: Programming Language :: Python :: 3.10
Classifier: Programming Language :: Python :: 3.11
Classifier: Programming Language :: Python :: 3.12
Classifier: Programming Language :: Python :: 3.13
Requires-Dist: streamlit
Project-URL: Repository, https://github.com/mjpallotta/msal_streamlit_authentication
